{"id":"LJFBVASF13S3G","name":"133_Synergy_Art_Tommy_Parker","size":22092,"btime":1687933058040,"mtime":1687933058040,"ext":"webp","tags":["Illustration"],"folders":["K8SIOHGZ9BPEQ"],"isDeleted":false,"url":"","annotation":"","modificationTime":1687933239462,"height":1200,"width":1200,"noThumbnail":true,"palettes":[{"color":[244,222,205],"ratio":87},{"color":[72,70,68],"ratio":7},{"color":[217,179,165],"ratio":1.38},{"color":[150,137,126],"ratio":1.06},{"color":[203,124,92],"ratio":0.99},{"color":[179,187,178],"ratio":0.76},{"color":[200,195,181],"ratio":0.7}],"lastModified":1687933244251}