{"id":"KYYO5146D5SIO","name":"Washing machine by Dimest on Dribbble","size":9723832,"btime":1643390281178,"mtime":1643390281204,"ext":"mp4","tags":[],"folders":[],"isDeleted":false,"url":"https://dribbble.com/shots/11322751-Washing-machine","annotation":"","modificationTime":1643390276838,"duration":10.069333,"height":1200,"width":1600,"lastModified":1643436135453,"palettes":[{"color":[235,238,244],"ratio":61},{"color":[36,38,46],"ratio":34},{"color":[247,155,26],"ratio":1.54},{"color":[139,153,161],"ratio":0.87},{"color":[81,89,109],"ratio":0.47},{"color":[43,158,233],"ratio":0.45},{"color":[174,101,182],"ratio":0.33}]}