{"id":"L166SZ8I33ME4","name":"Finance app - Mobile App","size":567362,"btime":1648198455157,"mtime":1648198455158,"ext":"png","tags":["Mobile","Finance"],"folders":["L166B8RR1MP1Q"],"isDeleted":false,"url":"https://dribbble.com/shots/17206553-Finance-app-Mobile-App/attachments/12308249?mode=media","annotation":"","modificationTime":1648198455138,"width":1600,"height":1200,"palettes":[{"color":[245,244,245],"ratio":51,"$$hashKey":"object:2042"},{"color":[10,10,10],"ratio":33,"$$hashKey":"object:2043"},{"color":[201,202,202],"ratio":7,"$$hashKey":"object:2044"},{"color":[234,232,142],"ratio":2.44,"$$hashKey":"object:2045"},{"color":[147,148,146],"ratio":1.72,"$$hashKey":"object:2046"},{"color":[75,75,67],"ratio":1.38,"$$hashKey":"object:2047"},{"color":[191,189,102],"ratio":1,"$$hashKey":"object:2048"},{"color":[126,100,96],"ratio":0.66,"$$hashKey":"object:2049"},{"color":[192,172,178],"ratio":0.35,"$$hashKey":"object:2050"}],"lastModified":1648198474867}