{"id":"KN1LRD0NXET4I","name":"Super team! teams remotework teamwork team dribbble illustrator charac","size":328873,"btime":1617446290000,"mtime":1617446290000,"ext":"jpg","tags":["illustration"],"folders":["K8SIOHGZ9BPEQ"],"isDeleted":false,"url":"https://dribbble.com/shots/15411785-Super-team/attachments/7178378?mode=media","annotation":"","modificationTime":1617446290343,"width":1600,"height":1188,"lastModified":1643436137180,"palettes":[{"color":[246,238,232],"ratio":59},{"color":[37,62,97],"ratio":7},{"color":[229,174,137],"ratio":7},{"color":[62,134,222],"ratio":6},{"color":[174,162,222],"ratio":5},{"color":[244,168,85],"ratio":4.53},{"color":[57,203,176],"ratio":4.48},{"color":[242,200,177],"ratio":1.98},{"color":[59,23,19],"ratio":1.06},{"color":[200,73,75],"ratio":0.8},{"color":[212,162,204],"ratio":0.33}]}