{"id":"KF473I18HUQS1","name":"Image may contain cartoon, drawing and illustration","size":142963,"ext":"jpg","tags":["illustration"],"folders":["K8SIOHGZ9BPEQ"],"isDeleted":false,"url":"https://www.behance.net/gallery/103918205/Personal-Illustration-Archive-3?tracking_source=best_of_behance","annotation":"","modificationTime":1600188802316,"width":1920,"height":1920,"lastModified":1643436135715,"palettes":[{"color":[250,249,249],"ratio":81},{"color":[36,31,30],"ratio":10},{"color":[97,185,219],"ratio":3.12},{"color":[224,188,160],"ratio":3.11},{"color":[204,206,206],"ratio":0.76},{"color":[144,181,192],"ratio":0.48}],"mtime":1600188802000,"btime":1600188802000}