{"id":"L7N1E1Q1VFEX4","name":"photo_6098030499013439636_y","size":91459,"btime":1668244850032,"mtime":1668244850033,"ext":"jpg","tags":[],"folders":["L6RLQQ8YC52UF"],"isDeleted":false,"url":"","annotation":"","modificationTime":1662277979471,"width":591,"height":1280,"noThumbnail":true,"palettes":[{"color":[250,250,250],"ratio":73},{"color":[56,114,198],"ratio":17},{"color":[26,24,29],"ratio":3.14},{"color":[150,170,191],"ratio":2.75},{"color":[94,95,97],"ratio":0.86},{"color":[232,159,33],"ratio":0.82},{"color":[7,42,101],"ratio":0.57},{"color":[201,85,95],"ratio":0.46}],"lastModified":1671517350795}