{"annotation":"","duration":12.053333,"ext":"mp4","folders":["K8T3RUN3R131N"],"height":1200,"id":"K8T4C3OVHUEYR","isDeleted":false,"modificationTime":1586458343001,"name":"Estudio I","palettes":[{"color":[239,239,246],"ratio":90},{"color":[181,220,234],"ratio":2.81},{"color":[149,171,222],"ratio":2.8},{"color":[85,113,228],"ratio":1.86},{"color":[209,215,226],"ratio":1.32}],"size":7103438,"tags":["interaction","mobile"],"url":"","width":1600,"lastModified":1643436137597,"mtime":1585786056000,"btime":1585786056000}